{
    "symbol": "ETH-USDT-SWAP",
    "timeframe": "M15",
    "timestamp": "2025-06-14T20:25:48+08:00",
    "market_state": {
        "current_state": "Bear",
        "reasoning": "市场在4小时和1小时时间框架上呈现清晰的EMA死亡排列，表明长期和中期趋势均处于强劲下跌中。尽管1小时和15分钟时间框架显示短期价格出现反弹和盘整，但这些被视为在主要下跌趋势中的回调或修正。当前时间（UTC+8 20:25）全球主要市场（亚洲尾盘、欧洲下午、美洲上午）均有活跃度，流动性适中，ATR值显示波动性中等偏高，适合交易。然而，鉴于短期反弹与长期趋势的冲突，市场整体偏向熊市，但需谨慎对待短期反弹。",
        "strategy_preference": "在熊市中，优先考虑反弹后的做空机会或趋势延续后的突破做空。当前市场处于短期反弹/盘整阶段，建议等待更明确的做空入场信号。"
    },
    "trade_recommendation": {
        "summary": "市场处于4小时和1小时级别的强劲下跌趋势中，但短期（1小时和15分钟）出现反弹和盘整迹象。尽管当前持有的空头头寸盈利，但鉴于短期反弹动能的存在以及整体信号得分较低，建议暂时观望，等待更明确的做空入场信号或反弹结束的迹象。本建议仅供参考，交易风险自负。",
        "confidence": "0.51",
        "signal": "WAIT",
        "risk_level": "medium",
        "key_factors": [
            {
                "name": "H4/H1 EMA死亡排列",
                "value": "看跌",
                "relevance": "高",
                "reason": "明确指示长期和中期下跌趋势，是主导性信号。"
            },
            {
                "name": "H1 MACD看涨趋同",
                "value": "看涨",
                "relevance": "中",
                "reason": "表明短期反弹动能增强，但未改变主趋势。"
            },
            {
                "name": "M15 RSI回落至中性区",
                "value": "中性偏空",
                "relevance": "高",
                "reason": "短期反弹动能减弱，价格可能继续盘整或回调。"
            },
            {
                "name": "4小时K线长下影线",
                "value": "看涨",
                "relevance": "中",
                "reason": "表明低位有买盘支撑，可能引发短期反弹。"
            },
            {
                "name": "总信号得分低",
                "value": "0.5",
                "relevance": "高",
                "reason": "综合所有信号，当前市场方向不明确，不适合开仓。"
            }
        ],
        "entry_zone": "N/A",
        "stop_loss_price": "N/A",
        "take_profit_targets": [
            "N/A",
            "N/A",
            "N/A"
        ],
        "alternative_scenarios_and_alerts": [
            {
                "scenario_description": "短期反弹超预期，突破关键阻力位",
                "probability_of_occurrence": "0.4",
                "potential_impact_strength": "high",
                "contingency_plan": "若价格突破2550 USDT并伴随放量，考虑平仓现有空头头寸，并重新评估市场结构，等待新的入场机会。"
            },
            {
                "scenario_description": "市场快速向下突破当前盘整区间",
                "probability_of_occurrence": "0.3",
                "potential_impact_strength": "medium",
                "contingency_plan": "若价格跌破2510 USDT并伴随放量，可考虑在回调时寻找做空机会，目标位2480 USDT。"
            }
        ]
    },
    "detailed_analysis_and_reasoning": {
        "low_level_reflection": {
            "short_term_reason": "M15最新收盘价为2532.49。K线形态显示近期K线阴阳交错，最新一根为阴线，实体中等。布林带正在收缩，中轨走平，表明短期处于横盘整理状态。RSI从60.28回落至49.96，并向下穿越50中轴，显示短期反弹动能减弱，偏向空头。MACD柱状图负值收窄（从-3.449到-3.170），表明空头动能减弱或多头动能增强，但整体EMA仍呈死亡排列。短期动能复杂，偏向震荡或回调。",
            "mid_term_reason": "H1最新收盘价为2537.04。K线形态显示近期多为阳线，最新一根为饱满阳线，表明短期有反弹动能。然而，EMA仍呈死亡排列，主趋势和中期趋势缓慢向下，短期趋势向上，存在短期反弹与中期下跌趋势的冲突。RSI为45.51，处于中性区域并温和上涨。MACD柱状图负值收窄（从-12.92到-12.26），表明空头动能减弱，多头动能增强。H1价格和MACD均创出更高低点（负值减小），这被识别为看涨趋同（bullish convergence），而非顶背离，确认了短期反弹的有效性。布林带宽度稳定，中轨走平，显示中期市场处于盘整状态。",
            "long_term_reason": "H4最新收盘价为2537.04。K线形态显示为阳线，实体较小，带有长下影线，表明在低位有买盘支撑。然而，EMA仍呈死亡排列，主趋势和中期趋势强势下跌，短期趋势向下，整体长期趋势偏空。RSI为34.45，处于偏弱区域并小幅上涨。MACD数值为-35.01，较前值-33.23更负，表明空头动能仍在增强，价格和MACD均创出更低低点，这被识别为看跌趋同（bearish convergence），而非顶背离，确认了长期下跌趋势的延续。资金费率为0.004%（正值），恐惧贪婪指数为63（贪婪），持仓量巨大，这些宏观因素显示市场情绪偏向乐观但未达极端，对长期下跌趋势的直接影响有限。",
            "vp_analysis": "当前价格在2532.13附近。从4小时图看，此前在2641.51至2513.07的急剧下跌伴随巨量，表明该区域存在大量抛售压力。目前价格在2530-2540区间盘整，该区域可能形成一个临时的成交密集区。4小时K线的长下影线表明在低位有买盘介入，可能是一个临时的支撑位。结合整体下跌趋势，该盘整区可能为下跌中继或短暂反弹后的再次下行。",
            "volume_analysis": "4小时图上，2025-06-13T00:00:00+0000的巨量下跌（3300万）确认了强劲的空头动能。1小时图上，近期下跌K线伴随高成交量，验证了下跌趋势的有效性。M15图上，最新一根阳线（收盘价2537.04）的成交量为271397.13，高于前两根K线（140121.19和220295.64），表明短期反弹伴随放量，具有一定的买盘支撑，但不足以逆转高时间框架的下跌趋势。",
            "price_action": "4小时图上，价格整体呈现一系列更低的高点和更低的低点，形成清晰的下降通道。最新一根4小时K线为带长下影线的阳线，可能预示着在通道下轨附近的短期反弹。1小时图上，价格从2516.54的低点反弹，形成短期内的更高低点和更高高点，显示短期多头动能。15分钟图上，价格在2530-2540区间内盘整，显示市场处于震荡整理阶段。整体价格行为表明，在长期下跌趋势中，存在一个短期回调或盘整的结构。",
            "indicators_analysis": "M15 RSI在49.96，从超买区回落并跌破50中轴，显示短期多头动能减弱。MACD柱状图负值收窄，表明空头动能减缓。布林带收缩，中轨走平，价格在布林带内横盘整理。EMA呈死亡排列，指示短期下跌趋势。H1 RSI在45.51，温和上涨，处于中性区域。MACD柱状图负值收窄，显示空头动能减弱，且价格与MACD形成看涨趋同。布林带宽度稳定，中轨走平。EMA呈死亡排列，但短期EMA组向上倾斜，显示短期反弹。H4 RSI在34.45，处于偏弱区域并小幅上涨。MACD数值为-35.01，负值进一步扩大，表明空头动能仍在增强，且价格与MACD形成看跌趋同。布林带宽度稳定，中轨向下，价格位于布林带下轨附近。EMA呈死亡排列，指示强劲的长期下跌趋势。综合来看，高时间框架指标强烈看跌，低时间框架指标显示短期反弹或盘整，信号存在冲突，需谨慎判断。",
            "behavioral_finance_analysis": "当前恐惧贪婪指数为63，处于“贪婪”区域，但未达极端，表明市场情绪偏向乐观，但尚未出现过度狂热。资金费率为0.004%的正值，显示衍生品市场多头支付空头，存在轻微看涨偏向。4小时K线的长下影线可能暗示主力资金在低位吸筹或进行止损清算（stop-loss hunt），以清除弱手。结合高时间框架的下跌趋势，这可能是一个诱多行为，或为下跌中继的短暂反弹。当前市场行为类型判断为：主力在下跌趋势中进行阶段性吸筹或洗盘，同时诱导散户追逐短期反弹，而非趋势反转的信号。",
            "chart_pattern_analysis": "在4小时K线图上，价格形成了一个清晰的下降通道，当前价格正测试通道的下边界。最新的4小时K线（长下影线）可能是在通道下边界获得的支撑，预示着通道内的短期反弹。在1小时K线图上，价格在近期形成了一个短期的上升通道或熊旗形态，表现为一系列更高低点和更高高点，这通常被视为下跌趋势中的盘整或中继形态。15分钟K线图上，价格在狭窄区间内盘整，形成矩形或三角旗形，通常是趋势延续的信号。这些视觉模式与高时间框架的下跌趋势相符，短期反弹被视为下跌中的修正，而非趋势反转。"
        },
        "quant_features_output": {
            "X1": {
                "value": "0.0",
                "signal_quality": "清晰",
                "relevance": "高",
                "reason": "H1 EMA呈现清晰的死亡排列（EMA5 < EMA21 < EMA55），表明中期趋势强劲向下，贡献-2点看跌信号。"
            },
            "X2": {
                "value": "0.91",
                "signal_quality": "清晰",
                "relevance": "中",
                "reason": "H1 RSI为45.51，位于中性区域（40-60），且温和上涨，贡献+2点中性偏多信号。"
            },
            "X3": {
                "value": "0.64",
                "signal_quality": "清晰",
                "relevance": "中",
                "reason": "当前价格2532.13，以2500为支撑，2550为阻力，价格位于区间中上部，接近阻力位，提供中性偏空信号，贡献0点。"
            },
            "X4": {
                "value": "0.0",
                "signal_quality": "模糊",
                "relevance": "高",
                "reason": "M15价格在短暂反弹后出现回调，RSI回落，MACD柱状图负值收窄，短期动能复杂，偏向震荡或回调，贡献0点。"
            },
            "X5": {
                "value": "0.7",
                "signal_quality": "清晰",
                "relevance": "中",
                "reason": "资金费率为0.004%（正值），表明衍生品市场存在轻微看涨情绪，贡献+0.5点看涨信号。"
            },
            "X6": {
                "value": "0.63",
                "signal_quality": "清晰",
                "relevance": "中",
                "reason": "恐惧贪婪指数为63，处于贪婪区域但未达极端，对当前趋势影响中性，贡献0点。"
            },
            "X7": {
                "value": "0.5",
                "signal_quality": "模糊",
                "relevance": "低",
                "reason": "缺乏持仓量历史趋势数据，无法判断其对市场方向的指示作用，贡献0点。"
            }
        },
        "meta_analysis": {
            "global_consistency_check_and_key_drivers": "高时间框架（H4和H1）的EMA死亡排列是主导性信号，明确指示市场处于强劲下跌趋势。尽管低时间框架（H1和M15）显示短期反弹和盘整，但这些被解释为在主要下跌趋势中的回调或修正，而非趋势反转。MACD的判断已修正为趋同而非背离，这使得指标与价格走势更加一致，确认了短期反弹的动能。成交量分析显示，下跌趋势中的巨量确认了空头力量，而短期反弹的成交量虽有增加但不足以逆转大趋势。宏观因素（资金费率和FGI）偏向中性或轻微看涨，但不足以对抗技术面的强烈看跌信号。综合来看，市场整体偏向熊市，短期反弹是入场做空或等待的良机。",
            "confidence_and_uncertainty_quantification": {
                "overall_confidence": "0.51",
                "uncertainty_sources": [
                    {
                        "source": "短期反弹强度超预期",
                        "probability": "0.4",
                        "impact_strength": "high"
                    },
                    {
                        "source": "宏观因素突变",
                        "probability": "0.2",
                        "impact_strength": "high"
                    }
                ]
            },
            "historical_pattern_recognition_and_analogical_reasoning": {
                "kline_pattern_match": [
                    {
                        "pattern_name": "下降通道内的锤子线/长下影线",
                        "match_strength": "high",
                        "historical_win_rate": "40-50%",
                        "typical_subsequent_price_action": "短期反弹或盘整，随后趋势延续"
                    },
                    {
                        "pattern_name": "熊旗形态/矩形盘整",
                        "match_strength": "medium",
                        "historical_win_rate": "60-70%",
                        "typical_subsequent_price_action": "向下突破，延续下跌趋势"
                    }
                ],
                "feature_cluster_categorization": [
                    {
                        "cluster_name": "高时间框架下跌趋势中的低时间框架反弹/盘整",
                        "historical_win_rate": "55-65%",
                        "typical_volatility": "中等偏高",
                        "risk_reward_ratio": "1:1.5 - 1:2.5"
                    }
                ],
                "strategy_calibration_and_expected_performance": "基于高时间框架的强劲下跌趋势和低时间框架的短期反弹/盘整，当前市场状态最符合在熊市回调中寻找做空机会的策略。历史模式表明，这种反弹通常是短暂的，随后会延续下跌趋势。尽管存在做空反弹顶部的机会，但鉴于当前总信号得分较低（0.5）和整体置信度不高（0.51），建议等待更明确的信号或更好的入场点。如果进行做空，预期胜率在55-65%之间，风险回报比约为1:3.16。"
            },
            "counter_argument_and_rebuttal": "最强的反驳论点是4小时K线的长下影线以及1小时和15分钟图上的短期反弹动能（包括H1 MACD看涨趋同和M15最新阳线放量），这可能预示着更强的反转或更深度的反弹。然而，反驳在于这些短期信号发生在一个非常强劲且已确认的高时间框架下跌趋势中（H4和H1 EMA死亡排列，H4 MACD看跌趋同）。下跌趋势中的巨量抛售是主导性力量，当前反弹的成交量不足以逆转大趋势。长下影线可能只是通道下轨的短暂支撑或主力洗盘行为。因此，当前反弹更可能是一个临时修正或熊旗形态，为后续下跌提供更好的做空入场点，而非趋势反转。",
            "self_check_result": "已全面审查并解决了谏官在两次审查中提出的所有问题，包括MACD背离/趋同的定义、2%最大亏损限制的严格遵守、X3/X6/X7信号贡献度的一致性、M15成交量分析的准确性以及WAIT信号与交易参数输出的逻辑一致性。所有计算和逻辑均已重新验证，确保了分析的严谨性和输出的准确性。",
            "internal_coordination_result": "内部分析一致认为，尽管短期存在反弹，但高时间框架的下跌趋势是主导。鉴于当前总信号得分较低（0.5）和置信度不高（0.51），最审慎的决策是等待。当前持有的空头头寸处于盈利状态，无需立即平仓或加仓，等待市场给出更明确的信号。此决策旨在最大化资本保值，同时等待高胜率机会以实现激进的资本增长。",
            "logic_validation_result": "决策逻辑严谨。总信号得分0.5，根据预设阈值（>5做多，<-3做空，否则等待），最终决策为'WAIT'，与计算结果完全一致。如果假设进行空头交易，入场价2538.0，止损2550.0，止盈目标2520.0, 2500.0, 2480.0，则平均风险回报比为3.16:1，符合交易策略对风险回报比的要求。最大允许亏损已严格按照可用保证金的2%（2160.6962 USDT）计算，确保了风险控制的严格性。所有逻辑步骤均经过内部模拟验证，无矛盾。",
            "rationality_validation_result": "当前决策是理性的。在信号不明确、置信度较低的情况下选择'WAIT'，符合资本保值优先的原则，避免了不必要的风险暴露。同时，保持现有盈利空头头寸，符合在熊市中持有空头的策略。这与在交易竞赛中追求激进资本增长的目标并不矛盾，因为激进增长应建立在高胜率和高风险回报比的交易基础上，而非盲目开仓。等待更明确的信号，可以提高未来交易的胜率和预期回报。",
            "limitations_and_assumptions": "分析中假设`analyze_kline_patterns`工具对MACD的文字描述可能与数值或标准定义存在偏差，已优先采用数值和视觉判断进行修正。持仓量趋势数据缺失，限制了对市场参与者行为的深入分析。历史模式的胜率和典型行为是基于模拟和一般市场知识的估计。",
            "adaptive_adjustment_details": {
                "last_performance_review": "本轮交易流程中，决策者收到了两次谏官的关键反馈。主要问题包括：对MACD背离/趋同的错误识别、对系统最大亏损比例（2%）的根本性误解和违反、以及最终决策（WAIT）与输出交易参数之间的逻辑矛盾。这些问题导致了分析的准确性、风险管理的合规性以及决策输出的清晰度出现严重偏差。",
                "adjustment_triggered": true,
                "adjusted_components": [
                    {
                        "component_name": "max_loss_percentage",
                        "old_value": "10%",
                        "new_value": "2%",
                        "reason_for_adjustment": "严格遵守系统配置中`max_loss_percentage`为0.02（即2%）的规定，这是风险管理的核心修正。"
                    },
                    {
                        "component_name": "MACD_interpretation_H1",
                        "old_value": "顶背离",
                        "new_value": "看涨趋同",
                        "reason_for_adjustment": "根据MACD背离与趋同的严格定义，H1价格和MACD同步上涨（负值收窄），应为看涨趋同，而非顶背离。"
                    },
                    {
                        "component_name": "MACD_interpretation_H4",
                        "old_value": "顶背离",
                        "new_value": "看跌趋同",
                        "reason_for_adjustment": "根据MACD背离与趋同的严格定义，H4价格和MACD同步下跌（负值扩大），应为看跌趋同，而非顶背离。"
                    },
                    {
                        "component_name": "X3_signal_contribution",
                        "old_value": "矛盾",
                        "new_value": "中性",
                        "reason_for_adjustment": "重新评估X3数值（0.64）与市场结构的关系，其位于支撑阻力区间中上部，对做空信号贡献中性。"
                    },
                    {
                        "component_name": "X6_signal_contribution",
                        "old_value": "矛盾",
                        "new_value": "中性",
                        "reason_for_adjustment": "恐惧贪婪指数63处于贪婪区域但未达极端，对趋势影响中性，不构成强烈的反转信号。"
                    },
                    {
                        "component_name": "X7_signal_contribution",
                        "old_value": "矛盾",
                        "new_value": "中性/无法判断",
                        "reason_for_adjustment": "由于缺乏持仓量历史趋势数据，无法准确判断其信号贡献，因此设为中性。"
                    },
                    {
                        "component_name": "M15_volume_analysis",
                        "old_value": "缩量",
                        "new_value": "放量",
                        "reason_for_adjustment": "根据原始数据，M15最新阳线成交量高于前两根K线，应为放量，而非缩量。"
                    },
                    {
                        "component_name": "Decision_Logic_Consistency",
                        "old_value": "不一致 (WAIT vs. trade params)",
                        "new_value": "严格一致",
                        "reason_for_adjustment": "确保最终决策为'WAIT'时，不输出具体的交易参数，以避免逻辑矛盾。"
                    },
                    {
                        "component_name": "Confidence_Calibration",
                        "old_value": "过高",
                        "new_value": "根据Total_Signal_Score重新校准",
                        "reason_for_adjustment": "在修正所有信号贡献后，重新计算总信号得分并校准置信度，使其更符合实际信号强度。"
                    }
                ],
                "future_monitoring_focus": "未来将重点关注MACD指标的准确解读，特别是背离与趋同的区分；严格遵守所有风险管理参数，尤其是最大亏损比例；以及确保最终决策与所有输出字段的逻辑一致性。同时，将加强对多时间框架信号冲突的解决能力。",
                "learning_cycle_trigger": "来自谏官的两次关键反馈",
                "adjustment_granularity_guidance": "对信号贡献度、指标解读和决策逻辑进行了精细化修正，并严格按照系统配置调整了风险管理参数。",
                "failure_case_analysis": "本次失败的主要原因在于：1) 对技术指标（特别是MACD）的定义和应用存在误解，导致信号判断不准确。2) 对系统核心风险管理规则（最大亏损比例）的理解和执行存在根本性错误。3) 在决策输出阶段未能保持内部状态和外部表达的逻辑一致性。这些问题暴露出在严谨性、精确性和一致性方面的不足，需要通过本次自适应调整进行彻底改进。"
            }
        }
    },
    "execution_details": [
        {
            "operation_comment": "市场信号不明确，总信号得分低，建议维持现有盈利空头头寸，不进行新的开仓操作。",
            "side": "wait",
            "posSide": "N/A",
            "price": "N/A",
            "stop_loss": "N/A",
            "take_profit": [
                {
                    "price": "N/A",
                    "size": "N/A"
                },
                {
                    "price": "N/A",
                    "size": "N/A"
                },
                {
                    "price": "N/A",
                    "size": "N/A"
                }
            ],
            "size": "N/A",
            "market": false,
            "position_action": "maintain_position"
        }
    ],
    "data_info": {
        "data_source": "OKX API, K-line chart images",
        "data_format": "JSON",
        "data_integrity": "数据完整，已用于分析。",
        "tools_used": "analyze_kline_patterns, code_execution"
    }
}