{
  "indicators_main(非实时报价)": {
    "15m": [
      {
        "开盘时间": "2025-06-09T15:00:00+0000",
        "open": 2529.54,
        "high": 2541.87,
        "low": 2528.58,
        "close": 2538.19,
        "volume": 544542.14,
        "RSI": 58.554,
        "EMA5": 2532.97,
        "EMA21": 2528.12,
        "EMA55": 2517.84,
        "ATR": 12.354,
        "MACD": 6.078,
        "VWAP": 2515.96
      },
      {
        "开盘时间": "2025-06-09T15:15:00+0000",
        "open": 2538.19,
        "high": 2541.0,
        "low": 2533.8,
        "close": 2540.49,
        "volume": 320855.49,
        "RSI": 60.766,
        "EMA5": 2535.48,
        "EMA21": 2529.24,
        "EMA55": 2518.65,
        "ATR": 11.667,
        "MACD": 6.319,
        "VWAP": 2516.18
      },
      {
        "开盘时间": "2025-06-09T15:30:00+0000",
        "open": 2540.49,
        "high": 2541.87,
        "low": 2534.0,
        "close": 2536.48,
        "volume": 231237.75,
        "RSI": 54.873,
        "EMA5": 2535.81,
        "EMA21": 2529.9,
        "EMA55": 2519.29,
        "ATR": 11.161,
        "MACD": 6.115,
        "VWAP": 2516.32
      },
      {
        "开盘时间": "2025-06-09T15:45:00+0000",
        "open": 2536.48,
        "high": 2540.3,
        "low": 2532.24,
        "close": 2532.91,
        "volume": 211197.92,
        "RSI": 49.902,
        "EMA5": 2534.84,
        "EMA21": 2530.17,
        "EMA55": 2519.77,
        "ATR": 10.747,
        "MACD": 5.601,
        "VWAP": 2516.44
      },
      {
        "开盘时间": "2025-06-09T16:00:00+0000",
        "open": 2532.91,
        "high": 2541.5,
        "low": 2532.79,
        "close": 2541.43,
        "volume": 268180.24,
        "RSI": 59.905,
        "EMA5": 2537.04,
        "EMA21": 2531.2,
        "EMA55": 2520.55,
        "ATR": 10.476,
        "MACD": 5.814,
        "VWAP": 2516.61
      },
      {
        "开盘时间": "2025-06-09T16:15:00+0000",
        "open": 2541.43,
        "high": 2569.71,
        "low": 2540.4,
        "close": 2566.01,
        "volume": 2278844.47,
        "RSI": 75.914,
        "EMA5": 2546.7,
        "EMA21": 2534.36,
        "EMA55": 2522.17,
        "ATR": 12.987,
        "MACD": 7.875,
        "VWAP": 2519.23
      },
      {
        "开盘时间": "2025-06-09T16:30:00+0000",
        "open": 2566.0,
        "high": 2572.0,
        "low": 2560.37,
        "close": 2566.38,
        "volume": 735721.96,
        "RSI": 76.079,
        "EMA5": 2553.26,
        "EMA21": 2537.27,
        "EMA55": 2523.75,
        "ATR": 12.806,
        "MACD": 9.43,
        "VWAP": 2520.16
      },
      {
        "开盘时间": "2025-06-09T16:45:00+0000",
        "open": 2566.38,
        "high": 2568.88,
        "low": 2555.6,
        "close": 2556.78,
        "volume": 606540.68,
        "RSI": 63.075,
        "EMA5": 2554.43,
        "EMA21": 2539.05,
        "EMA55": 2524.93,
        "ATR": 12.869,
        "MACD": 9.775,
        "VWAP": 2520.8
      },
      {
        "开盘时间": "2025-06-09T17:00:00+0000",
        "open": 2556.78,
        "high": 2570.92,
        "low": 2554.08,
        "close": 2568.97,
        "volume": 489023.04,
        "RSI": 70.47,
        "EMA5": 2559.28,
        "EMA21": 2541.77,
        "EMA55": 2526.5,
        "ATR": 13.399,
        "MACD": 10.906,
        "VWAP": 2521.36
      },
      {
        "开盘时间": "2025-06-09T17:15:00+0000",
        "open": 2568.97,
        "high": 2574.66,
        "low": 2563.37,
        "close": 2566.13,
        "volume": 516114.87,
        "RSI": 66.87,
        "EMA5": 2561.56,
        "EMA21": 2543.98,
        "EMA55": 2527.92,
        "ATR": 13.117,
        "MACD": 11.442,
        "VWAP": 2521.98
      }
    ],
    "1h": [
      {
        "开盘时间": "2025-06-09T07:00:00+0000",
        "open": 2492.01,
        "high": 2492.01,
        "low": 2482.0,
        "close": 2490.5,
        "volume": 829058.83,
        "RSI": 39.941,
        "EMA5": 2490.46,
        "EMA21": 2502.84,
        "EMA55": 2507.42,
        "ATR": 15.002,
        "MACD": -6.443,
        "VWAP": 2498.48
      },
      {
        "开盘时间": "2025-06-09T08:00:00+0000",
        "open": 2490.5,
        "high": 2495.8,
        "low": 2483.07,
        "close": 2493.93,
        "volume": 941392.67,
        "RSI": 44.316,
        "EMA5": 2491.61,
        "EMA21": 2502.03,
        "EMA55": 2506.94,
        "ATR": 14.699,
        "MACD": -6.268,
        "VWAP": 2498.43
      },
      {
        "开盘时间": "2025-06-09T09:00:00+0000",
        "open": 2493.92,
        "high": 2521.0,
        "low": 2489.56,
        "close": 2507.92,
        "volume": 2949328.25,
        "RSI": 58.531,
        "EMA5": 2497.05,
        "EMA21": 2502.57,
        "EMA55": 2506.97,
        "ATR": 16.931,
        "MACD": -4.943,
        "VWAP": 2498.58
      },
      {
        "开盘时间": "2025-06-09T10:00:00+0000",
        "open": 2507.91,
        "high": 2539.9,
        "low": 2507.8,
        "close": 2533.79,
        "volume": 3623193.14,
        "RSI": 73.154,
        "EMA5": 2509.3,
        "EMA21": 2505.41,
        "EMA55": 2507.93,
        "ATR": 18.953,
        "MACD": -1.785,
        "VWAP": 2499.28
      },
      {
        "开盘时间": "2025-06-09T11:00:00+0000",
        "open": 2533.79,
        "high": 2546.47,
        "low": 2528.0,
        "close": 2540.75,
        "volume": 2445523.33,
        "RSI": 75.803,
        "EMA5": 2519.78,
        "EMA21": 2508.62,
        "EMA55": 2509.1,
        "ATR": 18.889,
        "MACD": 1.265,
        "VWAP": 2499.91
      },
      {
        "开盘时间": "2025-06-09T12:00:00+0000",
        "open": 2540.74,
        "high": 2547.91,
        "low": 2533.15,
        "close": 2544.21,
        "volume": 1239491.03,
        "RSI": 77.099,
        "EMA5": 2527.92,
        "EMA21": 2511.86,
        "EMA55": 2510.36,
        "ATR": 18.338,
        "MACD": 3.916,
        "VWAP": 2500.25
      },
      {
        "开盘时间": "2025-06-09T13:00:00+0000",
        "open": 2544.22,
        "high": 2545.15,
        "low": 2508.01,
        "close": 2515.9,
        "volume": 3081640.03,
        "RSI": 51.205,
        "EMA5": 2523.92,
        "EMA21": 2512.22,
        "EMA55": 2510.55,
        "ATR": 20.845,
        "MACD": 3.69,
        "VWAP": 2500.7
      },
      {
        "开盘时间": "2025-06-09T14:00:00+0000",
        "open": 2515.9,
        "high": 2538.9,
        "low": 2512.8,
        "close": 2529.55,
        "volume": 2530043.99,
        "RSI": 58.887,
        "EMA5": 2525.79,
        "EMA21": 2513.8,
        "EMA55": 2511.23,
        "ATR": 21.546,
        "MACD": 4.559,
        "VWAP": 2501.12
      },
      {
        "开盘时间": "2025-06-09T15:00:00+0000",
        "open": 2529.54,
        "high": 2541.87,
        "low": 2528.58,
        "close": 2532.91,
        "volume": 1307833.3,
        "RSI": 60.647,
        "EMA5": 2528.17,
        "EMA21": 2515.54,
        "EMA55": 2512.01,
        "ATR": 20.445,
        "MACD": 5.457,
        "VWAP": 2501.39
      },
      {
        "开盘时间": "2025-06-09T16:00:00+0000",
        "open": 2532.91,
        "high": 2572.0,
        "low": 2532.79,
        "close": 2556.78,
        "volume": 3889287.35,
        "RSI": 70.868,
        "EMA5": 2537.7,
        "EMA21": 2519.29,
        "EMA55": 2513.61,
        "ATR": 22.947,
        "MACD": 8.002,
        "VWAP": 2502.64
      }
    ],
    "4h": [
      {
        "开盘时间": "2025-06-08T00:00:00+0000",
        "open": 2523.51,
        "high": 2524.87,
        "low": 2506.47,
        "close": 2510.43,
        "volume": 2651158.4,
        "RSI": 49.373,
        "EMA5": 2510.73,
        "EMA21": 2520.64,
        "EMA55": 2546.32,
        "ATR": 34.709,
        "MACD": -16.854,
        "VWAP": 2574.92
      },
      {
        "开盘时间": "2025-06-08T04:00:00+0000",
        "open": 2510.44,
        "high": 2518.73,
        "low": 2507.0,
        "close": 2513.39,
        "volume": 1918753.33,
        "RSI": 50.764,
        "EMA5": 2511.62,
        "EMA21": 2519.98,
        "EMA55": 2545.15,
        "ATR": 31.646,
        "MACD": -15.301,
        "VWAP": 2574.72
      },
      {
        "开盘时间": "2025-06-08T08:00:00+0000",
        "open": 2513.39,
        "high": 2519.7,
        "low": 2488.0,
        "close": 2512.07,
        "volume": 5262764.61,
        "RSI": 50.056,
        "EMA5": 2511.77,
        "EMA21": 2519.26,
        "EMA55": 2543.96,
        "ATR": 31.653,
        "MACD": -14.014,
        "VWAP": 2574.12
      },
      {
        "开盘时间": "2025-06-08T12:00:00+0000",
        "open": 2512.06,
        "high": 2527.21,
        "low": 2498.58,
        "close": 2513.3,
        "volume": 4151747.31,
        "RSI": 50.794,
        "EMA5": 2512.28,
        "EMA21": 2518.72,
        "EMA55": 2542.87,
        "ATR": 31.25,
        "MACD": -12.749,
        "VWAP": 2573.7
      },
      {
        "开盘时间": "2025-06-08T16:00:00+0000",
        "open": 2513.29,
        "high": 2539.5,
        "low": 2510.99,
        "close": 2531.38,
        "volume": 3622721.2,
        "RSI": 60.65,
        "EMA5": 2518.65,
        "EMA21": 2519.87,
        "EMA55": 2542.46,
        "ATR": 30.884,
        "MACD": -10.17,
        "VWAP": 2573.42
      },
      {
        "开盘时间": "2025-06-08T20:00:00+0000",
        "open": 2531.38,
        "high": 2548.0,
        "low": 2498.68,
        "close": 2508.51,
        "volume": 4460589.13,
        "RSI": 46.93,
        "EMA5": 2515.27,
        "EMA21": 2518.84,
        "EMA55": 2541.25,
        "ATR": 33.343,
        "MACD": -9.857,
        "VWAP": 2573.02
      },
      {
        "开盘时间": "2025-06-09T00:00:00+0000",
        "open": 2508.52,
        "high": 2511.05,
        "low": 2481.01,
        "close": 2495.52,
        "volume": 4673177.67,
        "RSI": 40.871,
        "EMA5": 2508.68,
        "EMA21": 2516.72,
        "EMA55": 2539.61,
        "ATR": 32.902,
        "MACD": -10.537,
        "VWAP": 2572.43
      },
      {
        "开盘时间": "2025-06-09T04:00:00+0000",
        "open": 2495.5,
        "high": 2495.99,
        "low": 2475.77,
        "close": 2490.5,
        "volume": 3773754.71,
        "RSI": 38.646,
        "EMA5": 2502.62,
        "EMA21": 2514.33,
        "EMA55": 2537.86,
        "ATR": 31.211,
        "MACD": -11.349,
        "VWAP": 2571.92
      },
      {
        "开盘时间": "2025-06-09T08:00:00+0000",
        "open": 2490.5,
        "high": 2546.47,
        "low": 2483.07,
        "close": 2540.75,
        "volume": 9959437.39,
        "RSI": 62.331,
        "EMA5": 2515.33,
        "EMA21": 2516.73,
        "EMA55": 2537.96,
        "ATR": 35.503,
        "MACD": -7.848,
        "VWAP": 2571.15
      },
      {
        "开盘时间": "2025-06-09T12:00:00+0000",
        "open": 2540.74,
        "high": 2547.91,
        "low": 2508.01,
        "close": 2532.91,
        "volume": 8159008.35,
        "RSI": 58.28,
        "EMA5": 2521.19,
        "EMA21": 2518.2,
        "EMA55": 2537.78,
        "ATR": 36.089,
        "MACD": -5.641,
        "VWAP": 2570.62
      }
    ]
  },
  "factors_main": {
    "factors": {
      "open_interest": "$3466961548739.012 million",
      "funding_rate": "0.01%",
      "FGI": null
    }
  },
  "okx_positions": {
    "instrument_id": "ETH-USDT-SWAP",
    "balance": {
      "Available_Margin": "113516.51 USDT"
    },
    "positions": {
      "instrument_id": "ETH-USDT-SWAP",
      "Margin_Model": "cross",
      "Position direction": "net",
      "pos": "-370.53 piece",
      "avgPrice": "2488.8855574447413166 USDT",
      "Unrealized Gains": "-2664.2753100000045 USDT",
      "liqPrice": "5624.671766601142 USDT",
      "lever": "100 x"
    },
    "orders": {
      "size": "N/A",
      "price": "N/A",
      "lever": "N/A",
      "direction": "N/A",
      "status": "N/A",
      "algo_orders": {}
    }
  },
  "current_time": "2025-06-10 01:36:46.388097+08:00",
  "kline_patterns": {
    "15m": {
      "kline_shapes": {
        "description": "阴线，实体较小，长上影线，近期多为阴线",
        "strength": "高"
      },
      "bollinger_bands": {
        "description": "价格在布林带内，位于89.5%处（0%为下轨，100%为上轨），布林带扩张7.4%，日均波动0.1%，中轨走平，横盘整理，布林带宽度占中轨2.4%",
        "strength": "中"
      },
      "ema_alignment": {
        "description": "EMA黄金排列，主趋势缓慢向上，中期趋势向上，短期趋势向上",
        "strength": "高"
      },
      "long_term_ema": {
        "description": "当前价格位于长期均线上方，长期趋势偏多",
        "strength": "强"
      },
      "rsi_analysis": {
        "description": "RSI偏强区域（66.9），RSI小幅下跌3.6点，RSI中等波动（振幅13.0点，日均波动6.0点），RSI频繁转向",
        "strength": "中"
      },
      "macd_analysis": {
        "description": "MACD柱形温和增长(0.056)，MACD趋势强劲(11.442)，趋势减速",
        "strength": "高"
      },
      "adx_analysis": {
        "description": "当前趋势开始形成，趋势增强持续性好",
        "strength": "中"
      },
      "stochastic": {
        "description": "KD指标处于超买区域，KD指标趋于钝化",
        "strength": "弱"
      },
      "stoch_rsi": {
        "description": "StochRSI形成死叉，StochRSI动能强劲下降",
        "strength": "强"
      }
    },
    "1h": {
      "kline_shapes": {
        "description": "阳线，实体中等，三连阳",
        "strength": "高"
      },
      "bollinger_bands": {
        "description": "价格在布林带内，位于99.1%处（0%为下轨，100%为上轨），布林带扩张10.0%，日均波动0.2%，中轨走平，横盘整理，布林带宽度占中轨3.6%",
        "strength": "高"
      },
      "ema_alignment": {
        "description": "EMA黄金排列，主趋势缓慢向上，中期趋势向上，短期趋势爆发性上涨",
        "strength": "高"
      },
      "long_term_ema": {
        "description": "当前价格位于长期均线上方，价格紧贴200均线，趋势不明确",
        "strength": "弱"
      },
      "rsi_analysis": {
        "description": "RSI超买（70.9），RSI强势上涨10.2点，RSI大幅波动（振幅25.9点，日均波动11.4点），市场情绪剧烈，RSI趋势连续性强",
        "strength": "高"
      },
      "macd_analysis": {
        "description": "MACD柱形快速增长(1.273)，MACD趋势强劲(8.002)，趋势加速",
        "strength": "高"
      },
      "adx_analysis": {
        "description": "当前趋势开始形成，趋势增强持续性好",
        "strength": "中"
      },
      "stochastic": {
        "description": "KD指标在中性区域，KD指标趋于钝化",
        "strength": "弱"
      },
      "stoch_rsi": {
        "description": "StochRSI显示超买",
        "strength": "中"
      }
    },
    "4h": {
      "kline_shapes": {
        "description": "阴线，实体较小，长下影线，近期多为阴线",
        "strength": "高"
      },
      "bollinger_bands": {
        "description": "价格在布林带内，位于85.5%处（0%为下轨，100%为上轨），布林带收缩10.3%，日均波动0.2%，中轨向上0.2%，趋势动量0.2，布林带宽度占中轨3.0%",
        "strength": "高"
      },
      "ema_alignment": {
        "description": "EMA散乱排列，主趋势缓慢向下，中期趋势向上，短期趋势向上",
        "strength": "中"
      },
      "long_term_ema": {
        "description": "当前价格位于长期均线下方，长期趋势偏空",
        "strength": "强"
      },
      "rsi_analysis": {
        "description": "RSI偏强区域（58.3），RSI小幅下跌4.1点，RSI大幅波动（振幅23.7点，日均波动9.0点），市场情绪剧烈，RSI频繁转向",
        "strength": "高"
      },
      "macd_analysis": {
        "description": "MACD柱形快速增长(0.879)，MACD趋势强劲(5.641)，趋势减速",
        "strength": "高"
      },
      "adx_analysis": {
        "description": "当前无明显趋势，趋势增强持续性好",
        "strength": "弱"
      },
      "stochastic": {
        "description": "KD指标在中性区域，KD指标呈上升趋势",
        "strength": "中"
      },
      "stoch_rsi": {
        "description": "StochRSI显示超买，StochRSI动能强劲上升",
        "strength": "中"
      }
    }
  },
  "tools_performance": {
    "gettime_exec_time": 1.5974044799804688e-05,
    "gettransactionhistory_exec_time": 0.0,
    "executepythoncode_exec_times": [],
    "analyzeklinepatterns_exec_time": 0.0001850128173828125
  },
  "timestamp": "2025-06-10T01:36:50+08:00"
}